{"Abyz":{"name":"Abyz","system":"A","production":3,"influence":0,"skip":null,"type":"Hazardous"},"Fria":{"name":"Fria","system":"A","production":2,"influence":0,"skip":null,"type":"Hazardous"},"Arinam":{"name":"Arinam","system":"B","production":1,"influence":2,"skip":null,"type":"Industrial"},"Meer":{"name":"Meer","system":"B","production":0,"influence":4,"skip":"Red","type":"Hazardous"},"Arnor":{"name":"Arnor","system":"C","production":2,"influence":1,"skip":null,"type":"Industrial"},"Lor":{"name":"Lor","system":"C","production":1,"influence":2,"skip":null,"type":"Industrial"},"Bereg":{"name":"Bereg","system":"D","production":3,"influence":1,"skip":null,"type":"Hazardous"},"Lirta IV":{"name":"Lirta IV","system":"D","production":2,"influence":3,"skip":null,"type":"Hazardous"},"Centauri":{"name":"Centauri","system":"E","production":1,"influence":3,"skip":null,"type":"Cultural"},"Gral":{"name":"Gral","system":"E","production":1,"influence":1,"skip":"Blue","type":"Industrial"},"Coorneeq":{"name":"Coorneeq","system":"F","production":1,"influence":2,"skip":null,"type":"Cultural"},"Resculon":{"name":"Resculon","system":"F","production":2,"influence":0,"skip":null,"type":"Cultural"},"Dal Bootha":{"name":"Dal Bootha","system":"G","production":0,"influence":2,"skip":null,"type":"Cultural"},"XXehan":{"name":"XXehan","system":"G","production":1,"influence":1,"skip":null,"type":"Cultural"},"Lazar":{"name":"Lazar","system":"H","production":1,"influence":0,"skip":"Yellow","type":"Industrial"},"Sakulag":{"name":"Sakulag","system":"H","production":2,"influence":1,"skip":null,"type":"Hazardous"},"Lodor":{"name":"Lodor","system":"I","production":3,"influence":1,"skip":null,"type":"Cultural"},"Mecatol Rex":{"name":"Mecatol Rex","system":"J","production":1,"influence":6,"skip":null,"type":null},"Mehar Xull":{"name":"Mehar Xull","system":"K","production":1,"influence":3,"skip":"Red","type":"Hazardous"},"Mellon":{"name":"Mellon","system":"L","production":0,"influence":2,"skip":null,"type":"Cultural"},"Zohbat":{"name":"Zohbat","system":"L","production":3,"influence":1,"skip":null,"type":"Hazardous"},"New Albion":{"name":"New Albion","system":"M","production":1,"influence":1,"skip":null,"type":"Industrial"},"Starpoint":{"name":"Starpoint","system":"M","production":3,"influence":1,"skip":null,"type":"Hazardous"},"Quann":{"name":"Quann","system":"N","production":2,"influence":1,"skip":null,"type":"Cultural"},"Qucen'n":{"name":"Qucen'n","system":"O","production":1,"influence":2,"skip":null,"type":"Industrial"},"Rarron":{"name":"Rarron","system":"O","production":0,"influence":3,"skip":null,"type":"Cultural"},"Saudor":{"name":"Saudor","system":"P","production":2,"influence":2,"skip":null,"type":"Industrial"},"Tar'Mann":{"name":"Tar'Mann","system":"Q","production":1,"influence":1,"skip":"Green","type":"Industrial"},"Tequ'ran":{"name":"Tequ'ran","system":"R","production":2,"influence":0,"skip":null,"type":"Hazardous"},"Torkan":{"name":"Torkan","system":"R","production":0,"influence":3,"skip":null,"type":"Cultural"},"Thibah":{"name":"Thibah","system":"S","production":1,"influence":1,"skip":"Blue","type":"Industrial"},"Vefut II":{"name":"Vefut II","system":"T","production":2,"influence":2,"skip":null,"type":"Hazardous"},"Wellon":{"name":"Wellon","system":"U","production":1,"influence":2,"skip":"Yellow","type":"Industrial"}}
